{
  "timestamp_utc": "2026-06-29T08:06:45+00:00",
  "estado_global": "OK",
  "alertas": [],
  "rechazos_1h": {
    "rango": 0,
    "spike": 0,
    "total": 0,
    "por_sym": {}
  },
  "assets": {
    "BTC": {
      "estado": "OK",
      "n": 5919,
      "age_seconds": 3.4,
      "ultimo_precio": 59978.395,
      "gaps": [],
      "alertas": []
    },
    "ETH": {
      "estado": "OK",
      "n": 5919,
      "age_seconds": 3.4,
      "ultimo_precio": 1579.21,
      "gaps": [],
      "alertas": []
    },
    "SOL": {
      "estado": "OK",
      "n": 5919,
      "age_seconds": 3.4,
      "ultimo_precio": 72.72,
      "gaps": [],
      "alertas": []
    },
    "XRP": {
      "estado": "OK",
      "n": 5919,
      "age_seconds": 3.4,
      "ultimo_precio": 1.0487,
      "gaps": [],
      "alertas": []
    }
  },
  "cross_source": {}
}