{
  "timestamp_utc": "2026-07-02T10:33:20+00:00",
  "estado_global": "OK",
  "alertas": [
    "rechazos_1h:5 (rango=0, spike=0)"
  ],
  "rechazos_1h": {
    "rango": 0,
    "spike": 0,
    "total": 5,
    "cambio_fuente": 88,
    "por_sym": {
      "SOL": 1,
      "XRP": 4
    }
  },
  "assets": {
    "BTC": {
      "estado": "OK",
      "n": 5506,
      "age_seconds": 1.1,
      "ultimo_precio": 61088.445,
      "gaps": [],
      "alertas": []
    },
    "ETH": {
      "estado": "OK",
      "n": 5506,
      "age_seconds": 1.1,
      "ultimo_precio": 1642.16,
      "gaps": [],
      "alertas": []
    },
    "SOL": {
      "estado": "OK",
      "n": 5506,
      "age_seconds": 1.1,
      "ultimo_precio": 80.45,
      "gaps": [],
      "alertas": []
    },
    "XRP": {
      "estado": "OK",
      "n": 5506,
      "age_seconds": 1.1,
      "ultimo_precio": 1.0779,
      "gaps": [],
      "alertas": []
    }
  },
  "cross_source": {
    "timestamp_utc": "2026-07-02T10:28:30+00:00",
    "fuentes_activas": [
      "binance",
      "coinbase",
      "kraken"
    ],
    "consenso": {
      "BTC": 61102.3,
      "ETH": 1642.88,
      "SOL": 80.19,
      "XRP": 1.07448
    },
    "alertas": [],
    "bloqueados": []
  }
}