{
  "timestamp_utc": "2026-07-02T15:24:52+00:00",
  "estado_global": "OK",
  "alertas": [],
  "rechazos_1h": {
    "rango": 0,
    "spike": 0,
    "total": 0,
    "cambio_fuente": 102,
    "por_sym": {}
  },
  "assets": {
    "BTC": {
      "estado": "OK",
      "n": 6386,
      "age_seconds": 3.5,
      "ultimo_precio": 61538.185,
      "gaps": [],
      "alertas": []
    },
    "ETH": {
      "estado": "OK",
      "n": 6386,
      "age_seconds": 3.5,
      "ultimo_precio": 1696.295,
      "gaps": [],
      "alertas": []
    },
    "SOL": {
      "estado": "OK",
      "n": 6386,
      "age_seconds": 3.5,
      "ultimo_precio": 80.69,
      "gaps": [],
      "alertas": []
    },
    "XRP": {
      "estado": "OK",
      "n": 6386,
      "age_seconds": 3.5,
      "ultimo_precio": 1.092,
      "gaps": [],
      "alertas": []
    }
  },
  "cross_source": {
    "timestamp_utc": "2026-07-02T15:21:14+00:00",
    "fuentes_activas": [
      "binance",
      "coinbase",
      "kraken"
    ],
    "consenso": {
      "BTC": 61538.185,
      "ETH": 1696.295,
      "SOL": 80.41,
      "XRP": 1.09002
    },
    "alertas": [],
    "bloqueados": []
  }
}