{
  "timestamp_utc": "2026-07-01T23:55:36+00:00",
  "estado_global": "OK",
  "alertas": [],
  "rechazos_1h": {
    "rango": 0,
    "spike": 0,
    "total": 0,
    "por_sym": {}
  },
  "assets": {
    "BTC": {
      "estado": "OK",
      "n": 7034,
      "age_seconds": 1.0,
      "ultimo_precio": 60012.665,
      "gaps": [],
      "alertas": []
    },
    "ETH": {
      "estado": "OK",
      "n": 7034,
      "age_seconds": 1.0,
      "ultimo_precio": 1609.285,
      "gaps": [],
      "alertas": []
    },
    "SOL": {
      "estado": "OK",
      "n": 7034,
      "age_seconds": 1.0,
      "ultimo_precio": 77.49,
      "gaps": [],
      "alertas": []
    },
    "XRP": {
      "estado": "OK",
      "n": 7034,
      "age_seconds": 1.0,
      "ultimo_precio": 1.0537,
      "gaps": [],
      "alertas": []
    }
  },
  "cross_source": {
    "timestamp_utc": "2026-07-01T23:55:11+00:00",
    "fuentes_activas": [
      "binance",
      "coinbase",
      "kraken"
    ],
    "consenso": {
      "BTC": 60021.1,
      "ETH": 1609.47,
      "SOL": 77.405,
      "XRP": 1.05258
    },
    "alertas": [],
    "bloqueados": []
  }
}