{
  "timestamp_utc": "2026-06-28T11:47:36+00:00",
  "estado_global": "OK",
  "alertas": [],
  "rechazos_1h": {
    "rango": 0,
    "spike": 0,
    "total": 0,
    "por_sym": {}
  },
  "assets": {
    "BTC": {
      "estado": "OK",
      "n": 5501,
      "age_seconds": 3.6,
      "ultimo_precio": 60207.16,
      "gaps": [
        {
          "inicio": "2026-06-27T08:26:38",
          "fin": "2026-06-27T09:20:02",
          "duracion_min": 53.4
        },
        {
          "inicio": "2026-06-27T09:20:19",
          "fin": "2026-06-27T10:29:03",
          "duracion_min": 68.7
        }
      ],
      "alertas": []
    },
    "ETH": {
      "estado": "OK",
      "n": 5501,
      "age_seconds": 3.6,
      "ultimo_precio": 1579.19,
      "gaps": [
        {
          "inicio": "2026-06-27T08:26:38",
          "fin": "2026-06-27T09:20:02",
          "duracion_min": 53.4
        },
        {
          "inicio": "2026-06-27T09:20:19",
          "fin": "2026-06-27T10:29:03",
          "duracion_min": 68.7
        }
      ],
      "alertas": []
    },
    "SOL": {
      "estado": "OK",
      "n": 5501,
      "age_seconds": 3.6,
      "ultimo_precio": 71.85,
      "gaps": [
        {
          "inicio": "2026-06-27T08:26:38",
          "fin": "2026-06-27T09:20:02",
          "duracion_min": 53.4
        },
        {
          "inicio": "2026-06-27T09:20:19",
          "fin": "2026-06-27T10:29:03",
          "duracion_min": 68.7
        }
      ],
      "alertas": []
    },
    "XRP": {
      "estado": "OK",
      "n": 5501,
      "age_seconds": 3.6,
      "ultimo_precio": 1.0513,
      "gaps": [
        {
          "inicio": "2026-06-27T08:26:38",
          "fin": "2026-06-27T09:20:02",
          "duracion_min": 53.4
        },
        {
          "inicio": "2026-06-27T09:20:19",
          "fin": "2026-06-27T10:29:03",
          "duracion_min": 68.7
        }
      ],
      "alertas": []
    }
  },
  "cross_source": {}
}