{
  "timestamp_utc": "2026-07-02T13:14:10+00:00",
  "estado_global": "OK",
  "alertas": [
    "rechazos_1h:2 (rango=0, spike=0)"
  ],
  "rechazos_1h": {
    "rango": 0,
    "spike": 0,
    "total": 2,
    "cambio_fuente": 102,
    "por_sym": {
      "XRP": 1,
      "SOL": 1
    }
  },
  "assets": {
    "BTC": {
      "estado": "OK",
      "n": 5994,
      "age_seconds": 1.6,
      "ultimo_precio": 61635.735,
      "gaps": [],
      "alertas": []
    },
    "ETH": {
      "estado": "OK",
      "n": 5994,
      "age_seconds": 1.6,
      "ultimo_precio": 1669.55,
      "gaps": [],
      "alertas": []
    },
    "SOL": {
      "estado": "OK",
      "n": 5994,
      "age_seconds": 1.6,
      "ultimo_precio": 81.55,
      "gaps": [],
      "alertas": []
    },
    "XRP": {
      "estado": "OK",
      "n": 5994,
      "age_seconds": 1.6,
      "ultimo_precio": 1.0955,
      "gaps": [],
      "alertas": []
    }
  },
  "cross_source": {
    "timestamp_utc": "2026-07-02T13:13:24+00:00",
    "fuentes_activas": [
      "binance",
      "coinbase",
      "kraken"
    ],
    "consenso": {
      "BTC": 61643.8,
      "ETH": 1669.55,
      "SOL": 81.57,
      "XRP": 1.09498
    },
    "alertas": [],
    "bloqueados": []
  }
}