{
  "timestamp_utc": "2026-07-01T19:28:27+00:00",
  "estado_global": "OK",
  "alertas": [],
  "rechazos_1h": {
    "rango": 0,
    "spike": 0,
    "total": 0,
    "por_sym": {}
  },
  "assets": {
    "BTC": {
      "estado": "OK",
      "n": 6217,
      "age_seconds": 2.9,
      "ultimo_precio": 60095.585,
      "gaps": [],
      "alertas": []
    },
    "ETH": {
      "estado": "OK",
      "n": 6217,
      "age_seconds": 2.9,
      "ultimo_precio": 1616.545,
      "gaps": [],
      "alertas": []
    },
    "SOL": {
      "estado": "OK",
      "n": 6217,
      "age_seconds": 2.9,
      "ultimo_precio": 77.26,
      "gaps": [],
      "alertas": []
    },
    "XRP": {
      "estado": "OK",
      "n": 6217,
      "age_seconds": 2.9,
      "ultimo_precio": 1.0623,
      "gaps": [],
      "alertas": []
    }
  },
  "cross_source": {
    "timestamp_utc": "2026-07-01T19:28:00+00:00",
    "fuentes_activas": [
      "binance",
      "coinbase",
      "kraken"
    ],
    "consenso": {
      "BTC": 60095.585,
      "ETH": 1616.66,
      "SOL": 77.15,
      "XRP": 1.06105
    },
    "alertas": [],
    "bloqueados": []
  }
}